wordlistenquiry/__init__.py
wordlistenquiry-1.0.1.dist-info/LICENCE.txt
wordlistenquiry-1.0.1.dist-info/METADATA
wordlistenquiry-1.0.1.dist-info/WHEEL
wordlistenquiry-1.0.1.dist-info/top_level.txt
wordlistenquiry-1.0.1.dist-info/RECORD
