Metadata-Version: 2.1
Name: wordlistenquiry
Version: 1.0.1
Summary: 查询单个单词/词组意思
Home-page: https://github.com/what-is-me/WordListEnquiry
Author: what-is-me
Author-email: leo.cai.nantong.china@gmail.com
License: UNKNOWN
Platform: UNKNOWN
Classifier: Programming Language :: Python :: 3
Classifier: License :: OSI Approved :: MIT License
Classifier: Operating System :: OS Independent
Requires-Python: >=3.6
